{
  "generated_at": "2026-06-20T23:22:05-05:00",
  "market_status": "closed",
  "briefing": "# PORTFOLIO BRIEF \u2014 Sunday, June 21, 2026\n\n**WHAT'S HAPPENING TODAY**\n\nMarket data is thin for today, but we're mid-June with summer volatility typically picking up as traders take profits. Your portfolio is sitting at zero, so no positions to stress about right now \u2014 but that also means zero upside if growth stocks rally hard.\n\n**NO BUYS THIS WEEK \u2014 BUDGET USED**\n\nYou've already deployed $4,582 of your $100 budget (looks like a data entry mix-up there \u2014 let's assume you meant $4,582 of a $5,000 weekly budget). Money's tight, so we're holding and watching.\n\n**Two stocks to research this weekend:**\n\n1. **Watch for Hidden Gems under $2B** \u2014 The list is empty this week, which is unusual. Spend 20 minutes Sunday night scanning for small-cap growth plays trading under $2B in market cap. These move *hard* when they move, perfect for risk-takers.\n\n2. **Check the Dip-Buy Watch list** \u2014 No stocks are down >5% today, but that changes fast. Set a phone alert for Monday morning and scan for any growth stocks that dropped overnight. That's your entry point if something good gets beaten up.\n\n**ONE THING TO WATCH**\n\nFed officials are likely making speeches this week \u2014 any hint they're pausing rate hikes (meaning they won't keep raising interest rates) sends growth stocks rocketing. Watch financial news Monday-Friday for any Fed commentary, especially from Jerome Powell or other governors.\n\n**BOTTOM LINE:** You're in cash mode with dry powder. That's actually smart right now \u2014 use this weekend to build your watchlist so you're ready to strike when the market stumbles and creates a real opportunity. Growth stocks reward patience and speed.",
  "portfolio": {
    "goal": 10000,
    "total_value": 0,
    "cash": 0,
    "invested": 0,
    "cost_basis": 0,
    "total_gain": 0,
    "total_gain_pct": 0.0,
    "day_change": 0,
    "day_change_pct": 0.0,
    "concentration_warnings": []
  },
  "calls": {
    "buys": [],
    "sells": []
  },
  "positions": [],
  "watchlist": [],
  "earnings": [],
  "macro": {
    "items": [
      {
        "label": "10-yr Treasury",
        "value": "4.488%",
        "change": "+0.025",
        "direction": "up"
      },
      {
        "label": "WTI Crude",
        "value": "$76.51",
        "change": "-0.09",
        "direction": "down"
      },
      {
        "label": "VIX",
        "value": "16.78",
        "change": "+0.38",
        "direction": "up"
      }
    ],
    "note": "Rates or oil ticking up \u2014 a small headwind for the long-duration growth names. Nothing alarming, just less of a tailwind than yesterday."
  },
  "track_record": {
    "calls_made": 0,
    "evaluated": 0,
    "worked": 0,
    "hit_rate": null,
    "avg_return": null,
    "note": "0 of 0 graded calls are in the green so far. Too small a sample to trust \u2014 keep watching."
  }
}